setup.cfg
setup.py
gwas_wrapper/__init__.py
gwas_wrapper/gwas_wrapper.py
gwas_wrapper.egg-info/PKG-INFO
gwas_wrapper.egg-info/SOURCES.txt
gwas_wrapper.egg-info/dependency_links.txt
gwas_wrapper.egg-info/not-zip-safe
gwas_wrapper.egg-info/top_level.txt