Metadata-Version: 1.1
Name: gwas-wrapper
Version: 0.1
Summary: Python wrapper for interacting with the NHGRI-EBI GWAS Catalog
Home-page: https://github.com/arvkevi/gwas_wrapper
Author: Kevin Arvai
Author-email: arvkevi@gmail.com
License: MIT
Download-URL: https://github.com/arvkevi/gwas_wrapper/tarball/0.1
Keywords: gwas,genomics,snp,bioinformatics
Platform: UNKNOWN
Classifier: Programming Language :: Python :: 2.7
Classifier: Topic :: Scientific/Engineering :: Bio-Informatics
